kdp_connector/__init__.py
kdp_connector/configuration/authenticationUtil.py
kdp_connector/configuration/configurationUtil.py
kdp_connector/configuration/keycloak_authentication.py
kdp_connector/configuration/proxy_authentication.py
kdp_connector/connectors/Storage.py
kdp_connector/connectors/audit_log.py
kdp_connector/connectors/audit_log_configs.py
kdp_connector/connectors/batch_write.py
kdp_connector/connectors/index_management.py
kdp_connector/connectors/ingest_job_api.py
kdp_connector/connectors/kdp_api.py
kdp_connector/connectors/query.py
kdp_connector/connectors/read.py
kdp_connector/connectors/upload.py
kdp_connector/main.py
kdp_python_connector-0.121.0.dist-info/METADATA
kdp_python_connector-0.121.0.dist-info/WHEEL
kdp_python_connector-0.121.0.dist-info/licenses/LICENSE
kdp_python_connector-0.121.0.dist-info/RECORD
